[
    {
        "model": "backend.tool",
        "pk": 1,
        "fields": {
            "type": "analytics",
            "product": "Google Analytics",
            "product_type": "",
            "free_tier": true,
            "free_limit": "100 Sites",
            "link": "https://analytics.google.com/",
            "img_source": "/static/Images/Analytics/google-analytics.svg"
        }
    },
    {
        "model": "backend.tool",
        "pk": 2,
        "fields": {
            "type": "analytics",
            "product": "Plausible",
            "product_type": "",
            "free_tier": false,
            "free_limit": "N/A",
            "link": "https://plausible.io/",
            "img_source": "/static/Images/Analytics/plausible.jpg"
        }
    },
    {
        "model": "backend.tool",
        "pk": 3,
        "fields": {
            "type": "database",
            "product": "Cloud Firestore",
            "product_type": "NoSQL",
            "free_tier": true,
            "free_limit": "1GiB",
            "link": "https://firebase.google.com/",
            "img_source": "/static/Images/Auth/firebase.svg"
        }
    },
    {
        "model": "backend.tool",
        "pk": 4,
        "fields": {
            "type": "database",
            "product": "MongoDB",
            "product_type": "NoSQL",
            "free_tier": true,
            "free_limit": "512 MB",
            "link": "https://www.mongodb.com/",
            "img_source": "/static/Images/Database/mongodb.svg"
        }
    },
    {
        "model": "backend.tool",
        "pk": 5,
        "fields": {
            "type": "database",
            "product": "FaunaDB",
            "product_type": "NoSQL",
            "free_tier": true,
            "free_limit": "100MB",
            "link": "https://fauna.com/",
            "img_source": "/static/Images/Database/fauna.png"
        }
    },
    {
        "model": "backend.tool",
        "pk": 6,
        "fields": {
            "type": "database",
            "product": "Heroku",
            "product_type": "SQL",
            "free_tier": true,
            "free_limit": "10k Rows",
            "link": "https://heroku.com/",
            "img_source": "/static/Images/Hosting/heroku.svg"
        }
    },
    {
        "model": "backend.tool",
        "pk": 7,
        "fields": {
            "type": "database",
            "product": "Amazon Web Services",
            "product_type": "Optional",
            "free_tier": true,
            "free_limit": "Depends On Service",
            "link": "https://aws.amazon.com/",
            "img_source": "/static/Images/Hosting/aws.svg"
        }
    },
    {
        "model": "backend.tool",
        "pk": 8,
        "fields": {
            "type": "database",
            "product": "Google Cloud",
            "product_type": "SQL",
            "free_tier": false,
            "free_limit": "N/A",
            "link": "https://cloud.google.com/",
            "img_source": "/static/Images/Hosting/google-cloud.svg"
        }
    },
    {
        "model": "backend.tool",
        "pk": 7,
        "fields": {
            "type": "database",
            "product": "Microsoft Azure",
            "product_type": "SQL",
            "free_tier": false,
            "free_limit": "N/A",
            "link": "https://azure.microsoft.com/",
            "img_source": "/static/Images/Hosting/azure.svg"
        }
    },
    {
        "model": "backend.tool",
        "pk": 8,
        "fields": {
            "type": "auth",
            "product": "Firebase Auth",
            "product_type": "Email/Password",
            "free_tier": true,
            "free_limit": "No Limit",
            "link": "https://firebase.google.com/",
            "img_source": "/static/Images/Auth/firebase.svg"
        }
    },
    {
        "model": "backend.tool",
        "pk": 9,
        "fields": {
            "type": "auth",
            "product": "Auth0",
            "product_type": "Email/Password",
            "free_tier": true,
            "free_limit": "7000",
            "link": "https://auth0.com/",
            "img_source": "/static/Images/Auth/auth0.svg"
        }
    },
    {
        "model": "backend.tool",
        "pk": 10,
        "fields": {
            "type": "frontend",
            "product": "React",
            "product_type": "42kB",
            "free_tier": false,
            "free_limit": "N/A",
            "link": "https://reactjs.org/",
            "img_source": "/static/Images/Frontend/react.svg"
        }
    },
    {
        "model": "backend.tool",
        "pk": 11,
        "fields": {
            "type": "frontend",
            "product": "Vue JS",
            "product_type": "20kB",
            "free_tier": false,
            "free_limit": "N/A",
            "link": "https://vuejs.org/",
            "img_source": "/static/Images/Frontend/vue.svg"
        }
    },
    {
        "model": "backend.tool",
        "pk": 12,
        "fields": {
            "type": "frontend",
            "product": "Angular",
            "product_type": "Depends",
            "free_tier": false,
            "free_limit": "N/A",
            "link": "https://angular.io/",
            "img_source": "/static/Images/Frontend/angular.svg"
        }
    },
    {
        "model": "backend.tool",
        "pk": 13,
        "fields": {
            "type": "backend",
            "product": "Express",
            "product_type": "Node.js",
            "free_tier": false,
            "free_limit": "",
            "link": "https://expressjs.com/",
            "img_source": "/static/Images/Backend/express.svg"
        }
    },
    {
        "model": "backend.tool",
        "pk": 14,
        "fields": {
            "type": "backend",
            "product": "Next.js",
            "product_type": "React",
            "free_tier": false,
            "free_limit": "",
            "link": "https://nextjs.org/",
            "img_source": "/static/Images/Backend/nextjs.svg"
        }
    },
    {
        "model": "backend.tool",
        "pk": 15,
        "fields": {
            "type": "backend",
            "product": "Flask",
            "product_type": "Python",
            "free_tier": false,
            "free_limit": "",
            "link": "https://flask.palletsprojects.com/en/1.1",
            "img_source": "/static/Images/Backend/flask.svg"
        }
    },
    {
        "model": "backend.tool",
        "pk": 16,
        "fields": {
            "type": "backend",
            "product": "Django",
            "product_type": "Python",
            "free_tier": false,
            "free_limit": "",
            "link": "https://www.djangoproject.com/",
            "img_source": "/static/Images/Backend/django.svg"
        }
    },
    {
        "model": "backend.tool",
        "pk": 17,
        "fields": {
            "type": "hosting",
            "product": "Vercel",
            "product_type": "Jamstack",
            "free_tier": true,
            "free_limit": "100 GB",
            "link": "https://vercel.com/dashboard",
            "img_source": "/static/Images/Hosting/vercel.svg"
        }
    },
    {
        "model": "backend.tool",
        "pk": 18,
        "fields": {
            "type": "hosting",
            "product": "Heroku",
            "product_type": "Full Server",
            "free_tier": true,
            "free_limit": "Low performance",
            "link": "https://heroku.com/",
            "img_source": "/static/Images/Hosting/heroku.svg"
        }
    },
    {
        "model": "backend.tool",
        "pk": 19,
        "fields": {
            "type": "hosting",
            "product": "Amazon Web Services",
            "product_type": "Full Cloud",
            "free_tier": true,
            "free_limit": "Low performance",
            "link": "https://aws.amazon.com/",
            "img_source": "/static/Images/Hosting/aws.svg"
        }
    },
    {
        "model": "backend.tool",
        "pk": 20,
        "fields": {
            "type": "hosting",
            "product": "Google Cloud",
            "product_type": "Full Cloud",
            "free_tier": true,
            "free_limit": "Low performance",
            "link": "https://cloud.google.com/",
            "img_source": "/static/Images/Hosting/google-cloud.svg"
        }
    },
    {
        "model": "backend.tool",
        "pk": 21,
        "fields": {
            "type": "hosting",
            "product": "Microsoft Azure",
            "product_type": "Full Cloud",
            "free_tier": true,
            "free_limit": "Low performance",
            "link": "https://azure.microsoft.com/en-us/",
            "img_source": "/static/Images/Hosting/azure.svg"
        }
    }
]